v4_proto/amino/amino_pb2.py
v4_proto/amino/amino_pb2.pyi
v4_proto/amino/amino_pb2_grpc.py
v4_proto/cosmos/app/runtime/v1alpha1/module_pb2.py
v4_proto/cosmos/app/runtime/v1alpha1/module_pb2.pyi
v4_proto/cosmos/app/runtime/v1alpha1/module_pb2_grpc.py
v4_proto/cosmos/app/v1alpha1/config_pb2.py
v4_proto/cosmos/app/v1alpha1/config_pb2.pyi
v4_proto/cosmos/app/v1alpha1/config_pb2_grpc.py
v4_proto/cosmos/app/v1alpha1/module_pb2.py
v4_proto/cosmos/app/v1alpha1/module_pb2.pyi
v4_proto/cosmos/app/v1alpha1/module_pb2_grpc.py
v4_proto/cosmos/app/v1alpha1/query_pb2.py
v4_proto/cosmos/app/v1alpha1/query_pb2.pyi
v4_proto/cosmos/app/v1alpha1/query_pb2_grpc.py
v4_proto/cosmos/auth/module/v1/module_pb2.py
v4_proto/cosmos/auth/module/v1/module_pb2.pyi
v4_proto/cosmos/auth/module/v1/module_pb2_grpc.py
v4_proto/cosmos/auth/v1beta1/auth_pb2.py
v4_proto/cosmos/auth/v1beta1/auth_pb2.pyi
v4_proto/cosmos/auth/v1beta1/auth_pb2_grpc.py
v4_proto/cosmos/auth/v1beta1/genesis_pb2.py
v4_proto/cosmos/auth/v1beta1/genesis_pb2.pyi
v4_proto/cosmos/auth/v1beta1/genesis_pb2_grpc.py
v4_proto/cosmos/auth/v1beta1/query_pb2.py
v4_proto/cosmos/auth/v1beta1/query_pb2.pyi
v4_proto/cosmos/auth/v1beta1/query_pb2_grpc.py
v4_proto/cosmos/auth/v1beta1/tx_pb2.py
v4_proto/cosmos/auth/v1beta1/tx_pb2.pyi
v4_proto/cosmos/auth/v1beta1/tx_pb2_grpc.py
v4_proto/cosmos/authz/module/v1/module_pb2.py
v4_proto/cosmos/authz/module/v1/module_pb2.pyi
v4_proto/cosmos/authz/module/v1/module_pb2_grpc.py
v4_proto/cosmos/authz/v1beta1/authz_pb2.py
v4_proto/cosmos/authz/v1beta1/authz_pb2.pyi
v4_proto/cosmos/authz/v1beta1/authz_pb2_grpc.py
v4_proto/cosmos/authz/v1beta1/event_pb2.py
v4_proto/cosmos/authz/v1beta1/event_pb2.pyi
v4_proto/cosmos/authz/v1beta1/event_pb2_grpc.py
v4_proto/cosmos/authz/v1beta1/genesis_pb2.py
v4_proto/cosmos/authz/v1beta1/genesis_pb2.pyi
v4_proto/cosmos/authz/v1beta1/genesis_pb2_grpc.py
v4_proto/cosmos/authz/v1beta1/query_pb2.py
v4_proto/cosmos/authz/v1beta1/query_pb2.pyi
v4_proto-9.6.0.dist-info/METADATA
v4_proto-9.6.0.dist-info/WHEEL
v4_proto-9.6.0.dist-info/top_level.txt
v4_proto-9.6.0.dist-info/RECORD
