Metadata-Version: 2.4
Name: v4-proto
Version: 9.6.0
Summary: Protos for dYdX Chain protocol
Author: dYdX Trading Inc.
Author-email: contact@dydx.exchange
Requires-Python: >=3.8
Requires-Dist: protobuf>=4.23
Requires-Dist: grpcio-tools>=1.54
Requires-Dist: grpcio>=1.54
Dynamic: author
Dynamic: author-email
Dynamic: requires-dist
Dynamic: requires-python
Dynamic: summary
